wingman/__init__.py
wingman/__main__.py
wingman/app.py
wingman/bulletin.py
wingman/checkpoints.py
wingman/command_completion.py
wingman/config.py
wingman/context.py
wingman/export.py
wingman/headless.py
wingman/images.py
wingman/lib/__init__.py
wingman/lib/oj.py
wingman/memory.py
wingman/sessions.py
wingman/tools.py
wingman/ui/__init__.py
wingman/ui/app.tcss
wingman/ui/modals.py
wingman/ui/welcome.py
wingman/ui/widgets.py
wingman_cli-0.4.3.dist-info/WHEEL
wingman_cli-0.4.3.dist-info/entry_points.txt
wingman_cli-0.4.3.dist-info/METADATA
wingman_cli-0.4.3.dist-info/RECORD
