Metadata-Version: 2.3
Name: wingman-cli
Version: 0.4.3
Summary: AI-powered TUI coding assistant for the terminal
Keywords: ai,coding,assistant,tui,terminal,cli,llm,gpt,claude,gemini
Author: Aryan Mahajan, Dedalus Labs
Author-email: Aryan Mahajan <aryan@dedalus.ai>, Dedalus Labs <oss@dedaluslabs.ai>
License: MIT
Classifier: Development Status :: 3 - Alpha
Classifier: Environment :: Console
Classifier: Intended Audience :: Developers
Classifier: License :: OSI Approved :: MIT License
Classifier: Operating System :: OS Independent
Classifier: Programming Language :: Python :: 3
Classifier: Programming Language :: Python :: 3.10
Classifier: Programming Language :: Python :: 3.11
Classifier: Programming Language :: Python :: 3.12
Classifier: Programming Language :: Python :: 3.13
Classifier: Topic :: Software Development
Classifier: Topic :: Terminals
Classifier: Topic :: Scientific/Engineering :: Artificial Intelligence
Classifier: Typing :: Typed
Requires-Dist: dedalus-labs>=0.1.1
Requires-Dist: textual>=0.50.0
Requires-Dist: rich>=13.0.0
Requires-Dist: httpx>=0.27.0
Requires-Dist: pillow>=10.0.0
Requires-Dist: pyyaml>=6.0
Requires-Dist: orjson>=3.10
Requires-Dist: python-dotenv>=1.0.0
Requires-Dist: pytest>=8.0.0 ; extra == 'dev'
Requires-Dist: pytest-asyncio>=0.23.0 ; extra == 'dev'
Requires-Dist: ruff>=0.14.0 ; extra == 'dev'
Requires-Dist: ty>=0.0.5 ; extra == 'dev'
Maintainer: Aryan Mahajan
Maintainer-email: Aryan Mahajan <aryan@dedalus.ai>
Requires-Python: >=3.10
Project-URL: Documentation, https://github.com/dedalus-labs/wingman#readme
Project-URL: Homepage, https://github.com/dedalus-labs/wingman
Project-URL: Issues, https://github.com/dedalus-labs/wingman/issues
Project-URL: Repository, https://github.com/dedalus-labs/wingman
Provides-Extra: dev
